mbdb/__init__.py
mbdb/mbdb.py
mbdb/parsetab.py
mbdb/sqlparser.py
mbdb-0.5.dist-info/LICENSE.md
mbdb-0.5.dist-info/METADATA
mbdb-0.5.dist-info/WHEEL
mbdb-0.5.dist-info/top_level.txt
mbdb-0.5.dist-info/RECORD
