Metadata-Version: 2.1
Name: mbdb
Version: 0.5
Summary: Simple Database Management System
Home-page: https://github.com/tonighty/mbdb
Author: mjr&bkva
Author-email: mjr@feip.co
License: UNKNOWN
Platform: UNKNOWN
Requires-Dist: ply
